service/__init__.py
service/pipeline_service.py
dlpipeline_api-0.0.6.dist-info/METADATA
dlpipeline_api-0.0.6.dist-info/WHEEL
dlpipeline_api-0.0.6.dist-info/top_level.txt
dlpipeline_api-0.0.6.dist-info/RECORD
